Metadata-Version: 1.1
Name: django-unslashed
Version: 0.3.0
Summary: Django Middleware that can automatically remove trailing URL slashes and 301 redirect to the non-slash-terminated URL.
Home-page: https://github.com/dghubble/django-unslashed
Author: Dalton Hubble
Author-email: dghubble@gmail.com
License: MIT License
Keywords: django slash remove trailing unslash remove_slash path
Platform: UNKNOWN
Classifier: Programming Language :: Python :: 2
Classifier: Programming Language :: Python :: 3
Classifier: License :: OSI Approved :: MIT License
Classifier: Operating System :: OS Independent
Classifier: Development Status :: 3 - Alpha
Classifier: Intended Audience :: Developers
Classifier: Framework :: Django
Classifier: Environment :: Web Environment
Classifier: Topic :: Internet :: WWW/HTTP
